file_read_backwards/__init__.py
file_read_backwards/buffer_work_space.py
file_read_backwards/file_read_backwards.py
file_read_backwards-3.2.0.dist-info/AUTHORS.rst
file_read_backwards-3.2.0.dist-info/LICENSE
file_read_backwards-3.2.0.dist-info/METADATA
file_read_backwards-3.2.0.dist-info/WHEEL
file_read_backwards-3.2.0.dist-info/top_level.txt
file_read_backwards-3.2.0.dist-info/RECORD
