Metadata-Version: 2.1
Name: file_read_backwards
Version: 3.2.0
Summary: Memory efficient way of reading files line-by-line from the end of file
Home-page: https://github.com/RobinNil/file_read_backwards
Author: Robin Robin
Author-email: robinsquare42@gmail.com
License: MIT
Keywords: file_read_backwards
Classifier: Development Status :: 5 - Production/Stable
Classifier: Intended Audience :: Developers
Classifier: Natural Language :: English
Classifier: Programming Language :: Python :: 3
Classifier: Programming Language :: Python :: 3.7
Classifier: Programming Language :: Python :: 3.8
Classifier: Programming Language :: Python :: 3.9
Classifier: Programming Language :: Python :: 3.10
Classifier: Programming Language :: Python :: 3.11
Classifier: Programming Language :: Python :: 3.12
Classifier: Programming Language :: Python :: 3.13
License-File: LICENSE
License-File: AUTHORS.rst
